elevenlabs/__init__.py
elevenlabs/audio_isolation/__init__.py
elevenlabs/audio_isolation/client.py
elevenlabs/audio_isolation/raw_client.py
elevenlabs/audio_isolation/types/__init__.py
elevenlabs/audio_isolation/types/audio_isolation_convert_request_file_format.py
elevenlabs/audio_isolation/types/audio_isolation_stream_request_file_format.py
elevenlabs/audio_native/__init__.py
elevenlabs/audio_native/client.py
elevenlabs/audio_native/raw_client.py
elevenlabs/audio_native/types/__init__.py
elevenlabs/audio_native/types/audio_native_create_request_apply_text_normalization.py
elevenlabs/base_client.py
elevenlabs/client.py
elevenlabs/conversational_ai/__init__.py
elevenlabs/conversational_ai/agents/__init__.py
elevenlabs/conversational_ai/agents/branches/__init__.py
elevenlabs/conversational_ai/agents/branches/client.py
elevenlabs/conversational_ai/agents/branches/raw_client.py
elevenlabs/conversational_ai/agents/client.py
elevenlabs/conversational_ai/agents/deployments/__init__.py
elevenlabs/conversational_ai/agents/deployments/client.py
elevenlabs/conversational_ai/agents/deployments/raw_client.py
elevenlabs/conversational_ai/agents/drafts/__init__.py
elevenlabs/conversational_ai/agents/drafts/client.py
elevenlabs/conversational_ai/agents/drafts/raw_client.py
elevenlabs/conversational_ai/agents/knowledge_base/__init__.py
elevenlabs/conversational_ai/agents/knowledge_base/client.py
elevenlabs/conversational_ai/agents/knowledge_base/raw_client.py
elevenlabs/conversational_ai/agents/link/__init__.py
elevenlabs/conversational_ai/agents/link/client.py
elevenlabs/conversational_ai/agents/link/raw_client.py
elevenlabs/conversational_ai/agents/llm_usage/__init__.py
elevenlabs/conversational_ai/agents/llm_usage/client.py
elevenlabs/conversational_ai/agents/llm_usage/raw_client.py
elevenlabs/conversational_ai/agents/raw_client.py
elevenlabs/conversational_ai/agents/summaries/__init__.py
elevenlabs/conversational_ai/agents/summaries/client.py
elevenlabs-2.33.1.dist-info/LICENSE
elevenlabs-2.33.1.dist-info/METADATA
elevenlabs-2.33.1.dist-info/WHEEL
elevenlabs-2.33.1.dist-info/RECORD
