Metadata-Version: 2.1
Name: elevenlabs
Version: 2.33.1
Summary: 
License: MIT
Requires-Python: >=3.8,<4.0
Classifier: Intended Audience :: Developers
Classifier: License :: OSI Approved :: MIT License
Classifier: Operating System :: MacOS
Classifier: Operating System :: Microsoft :: Windows
Classifier: Operating System :: OS Independent
Classifier: Operating System :: POSIX
Classifier: Operating System :: POSIX :: Linux
Classifier: Programming Language :: Python
Classifier: Programming Language :: Python :: 3
Classifier: Programming Language :: Python :: 3.8
Classifier: Programming Language :: Python :: 3.9
Classifier: Programming Language :: Python :: 3.10
Classifier: Programming Language :: Python :: 3.11
Classifier: Programming Language :: Python :: 3.12
Classifier: Topic :: Software Development :: Libraries :: Python Modules
Classifier: Typing :: Typed
Provides-Extra: pyaudio
Requires-Dist: httpx (>=0.21.2)
Requires-Dist: pyaudio (>=0.2.14) ; extra == "pyaudio"
Requires-Dist: pydantic (>=1.9.2)
Requires-Dist: pydantic-core (>=2.18.2)
Requires-Dist: requests (>=2.20)
Requires-Dist: typing_extensions (>=4.0.0)
Requires-Dist: websockets (>=11.0)
Project-URL: Repository, https://github.com/elevenlabs/elevenlabs-python
